prompt_stanza/__init__.py
prompt_stanza/ab_testing/__init__.py
prompt_stanza/ab_testing/multi_variant.py
prompt_stanza/builder/__init__.py
prompt_stanza/builder/defense.py
prompt_stanza/builder/delimiter.py
prompt_stanza/builder/prompt_builder.py
prompt_stanza/builder/validator.py
prompt_stanza/cli.py
prompt_stanza/core/__init__.py
prompt_stanza/core/prompt_stanza.py
prompt_stanza/defense_strategies/__init__.py
prompt_stanza/defense_strategies/base.py
prompt_stanza/defense_strategies/classify_intent.py
prompt_stanza/defense_strategies/perplexity_check.py
prompt_stanza/defense_strategies/rewrite.py
prompt_stanza/defense_strategies/sandwich.py
prompt_stanza/delimiter_strategies/__init__.py
prompt_stanza/delimiter_strategies/angle_brackets.py
prompt_stanza/delimiter_strategies/base.py
prompt_stanza/delimiter_strategies/markdown.py
prompt_stanza/delimiter_strategies/marker.py
prompt_stanza/delimiter_strategies/none_strategy.py
prompt_stanza/delimiter_strategies/xml.py
prompt_stanza/exceptions/__init__.py
prompt_stanza/exceptions/base.py
prompt_stanza/input_adapters/__init__.py
prompt_stanza/input_adapters/base.py
prompt_stanza/input_adapters/dynamodb_adapter.py
prompt_stanza/input_adapters/inline_adapter.py
prompt_stanza/input_adapters/local_file_adapter.py
prompt_stanza/input_adapters/mongodb_adapter.py
prompt_stanza/input_adapters/s3_file_adapter.py
prompt_stanza/input_adapters/sql_adapter.py
prompt_stanza/models/__init__.py
prompt_stanza/models/prompt_config.py
prompt_stanza/models/schema.py
prompt_stanza/models/strategies.py
prompt_stanza/models/template.py
prompt_stanza/output_adapters/__init__.py
prompt_stanza/output_adapters/base.py
prompt_stanza/output_adapters/langchain_output.py
prompt_stanza/output_adapters/string_output.py
prompt_stanza/py.typed
prompt_stanza/utils/__init__.py
prompt_stanza/utils/create_dynamodb_table.py
prompt_stanza/utils/create_mongodb_collection.py
prompt_stanza-0.0.1.dist-info/WHEEL
prompt_stanza-0.0.1.dist-info/entry_points.txt
prompt_stanza-0.0.1.dist-info/METADATA
prompt_stanza-0.0.1.dist-info/RECORD
