Metadata-Version: 2.3
Name: prompt-stanza
Version: 0.0.1
Summary: A comprehensive framework for composing, versioning, and securing LLM prompts with support for multiple input/output adapters, defense strategies, delimiters, and A/B testing capabilities
Author: Rahul Bairathi
Author-email: Rahul Bairathi <bairathirahul@gmail.com>
Requires-Dist: jinja2>=3.1.6
Requires-Dist: langchain>=1.1.3
Requires-Dist: pydantic>=2.12.5
Requires-Dist: pyyaml>=6.0.3
Requires-Dist: tiktoken>=0.12.0
Requires-Dist: sqlalchemy>=2.0.44 ; extra == 'all'
Requires-Dist: psycopg2-binary>=2.9.11 ; extra == 'all'
Requires-Dist: boto3>=1.42.4 ; extra == 'all'
Requires-Dist: pymongo>=4.15.5 ; extra == 'all'
Requires-Dist: boto3>=1.42.4 ; extra == 'aws'
Requires-Dist: langchain-openai>=0.2.0 ; extra == 'examples'
Requires-Dist: pymongo>=4.15.5 ; extra == 'mongo'
Requires-Dist: sqlalchemy>=2.0.44 ; extra == 'sql'
Requires-Dist: psycopg2-binary>=2.9.11 ; extra == 'sql'
Requires-Python: >=3.11
Provides-Extra: all
Provides-Extra: aws
Provides-Extra: examples
Provides-Extra: mongo
Provides-Extra: sql
